<?xml version="1.0" encoding="UTF-8"?>
    <!--
                 This_software_was_developed_and_/_or_modified_by_Raytheon_Company,
        pursuant_to_Contract_DG133W-05-CQ-1067_with_the_US_Government.

        U.S._EXPORT_CONTROLLED_TECHNICAL_DATA
        This_software_product_contains_export-restricted_data_whose
        export/transfer/disclosure_is_restricted_by_U.S._law._Dissemination
        to_non-U.S._persons_whether_in_the_United_States_or_abroad_requires
        an_export_license_or_other_authorization.

        Contractor_Name:________Raytheon_Company
        Contractor_Address:_____6825_Pine_Street,_Suite_340
        ________________________Mail_Stop_B8
        ________________________Omaha,_NE_68106
        ________________________402.291.0100

        See_the_AWIPS_II_Master_Rights_File_("Master_Rights_File.pdf")_for
        further_licensing_information.
    -->

    <!--
                 This is an absolute override file, indicating that a higher priority
        version of the file will completely replace a lower priority version
        of the file.
    -->
<gridParamInfo xmlns:ns2="group">
  <valtimeMINUSreftime>
    <fcst>0</fcst>
    <fcst>3600</fcst>
    <fcst>7200</fcst>
    <fcst>10800</fcst>
    <fcst>14400</fcst>
    <fcst>18000</fcst>
    <fcst>21600</fcst>
    <fcst>25200</fcst>
    <fcst>28800</fcst>
    <fcst>32400</fcst>
    <fcst>36000</fcst>
    <fcst>39600</fcst>
    <fcst>43200</fcst>
    <fcst>46800</fcst>
    <fcst>50400</fcst>
    <fcst>54000</fcst>
    <fcst>57600</fcst>
    <fcst>61200</fcst>
    <fcst>64800</fcst>
    <fcst>68400</fcst>
    <fcst>72000</fcst>
    <fcst>75600</fcst>
    <fcst>79200</fcst>
    <fcst>82800</fcst>
    <fcst>86400</fcst>
    <fcst>90000</fcst>
    <fcst>93600</fcst>
    <fcst>97200</fcst>
    <fcst>100800</fcst>
    <fcst>104400</fcst>
    <fcst>108000</fcst>
    <fcst>111600</fcst>
    <fcst>115200</fcst>
    <fcst>118800</fcst>
    <fcst>122400</fcst>
    <fcst>126000</fcst>
    <fcst>129600</fcst>
    <fcst>133200</fcst>
    <fcst>136800</fcst>
    <fcst>140400</fcst>
    <fcst>144000</fcst>
    <fcst>147600</fcst>
    <fcst>151200</fcst>
    <fcst>154800</fcst>
    <fcst>158400</fcst>
    <fcst>162000</fcst>
    <fcst>165600</fcst>
    <fcst>169200</fcst>
    <fcst>172800</fcst>
    <fcst>176400</fcst>
    <fcst>180000</fcst>
    <fcst>183600</fcst>
    <fcst>187200</fcst>
    <fcst>190800</fcst>
    <fcst>194400</fcst>
    <fcst>198000</fcst>
    <fcst>201600</fcst>
    <fcst>205200</fcst>
    <fcst>208800</fcst>
    <fcst>212400</fcst>
    <fcst>216000</fcst>
    <fcst>219600</fcst>
    <fcst>223200</fcst>
    <fcst>226800</fcst>
    <fcst>230400</fcst>
    <fcst>234000</fcst>
    <fcst>237600</fcst>
    <fcst>241200</fcst>
    <fcst>244800</fcst>
    <fcst>248400</fcst>
    <fcst>252000</fcst>
    <fcst>255600</fcst>
    <fcst>259200</fcst>
    <fcst>262800</fcst>
    <fcst>266400</fcst>
    <fcst>270000</fcst>
    <fcst>273600</fcst>
    <fcst>277200</fcst>
    <fcst>280800</fcst>
    <fcst>284400</fcst>
    <fcst>288000</fcst>
    <fcst>291600</fcst>
    <fcst>295200</fcst>
    <fcst>298800</fcst>
    <fcst>302400</fcst>
    <fcst>306000</fcst>
    <fcst>309600</fcst>
    <fcst>313200</fcst>
    <fcst>316800</fcst>
    <fcst>320400</fcst>
    <fcst>324000</fcst>
    <fcst>327600</fcst>
    <fcst>331200</fcst>
    <fcst>334800</fcst>
    <fcst>338400</fcst>
    <fcst>342000</fcst>
    <fcst>345600</fcst>
    <fcst>349200</fcst>
    <fcst>352800</fcst>
    <fcst>356400</fcst>
    <fcst>360000</fcst>
    <fcst>363600</fcst>
    <fcst>367200</fcst>
    <fcst>370800</fcst>
    <fcst>374400</fcst>
    <fcst>378000</fcst>
    <fcst>381600</fcst>
    <fcst>385200</fcst>
    <fcst>388800</fcst>
    <fcst>392400</fcst>
    <fcst>396000</fcst>
    <fcst>399600</fcst>
    <fcst>403200</fcst>
    <fcst>406800</fcst>
    <fcst>410400</fcst>
    <fcst>414000</fcst>
    <fcst>417600</fcst>
    <fcst>421200</fcst>
    <fcst>424800</fcst>
    <fcst>428400</fcst>
    <fcst>432000</fcst>
    <fcst>435600</fcst>
    <fcst>439200</fcst>
    <fcst>442800</fcst>
    <fcst>446400</fcst>
    <fcst>450000</fcst>
    <fcst>453600</fcst>
    <fcst>457200</fcst>
    <fcst>460800</fcst>
    <fcst>464400</fcst>
    <fcst>468000</fcst>
    <fcst>471600</fcst>
    <fcst>475200</fcst>
    <fcst>478800</fcst>
    <fcst>482400</fcst>
    <fcst>486000</fcst>
    <fcst>489600</fcst>
    <fcst>493200</fcst>
    <fcst>496800</fcst>
    <fcst>500400</fcst>
    <fcst>504000</fcst>
    <fcst>507600</fcst>
    <fcst>511200</fcst>
    <fcst>514800</fcst>
    <fcst>518400</fcst>
    <fcst>522000</fcst>
    <fcst>525600</fcst>
    <fcst>529200</fcst>
    <fcst>532800</fcst>
    <fcst>536400</fcst>
    <fcst>540000</fcst>
    <fcst>543600</fcst>
    <fcst>547200</fcst>
    <fcst>550800</fcst>
    <fcst>554400</fcst>
    <fcst>558000</fcst>
    <fcst>561600</fcst>
    <fcst>565200</fcst>
    <fcst>568800</fcst>
    <fcst>572400</fcst>
    <fcst>576000</fcst>
    <fcst>579600</fcst>
    <fcst>583200</fcst>
    <fcst>586800</fcst>
    <fcst>590400</fcst>
    <fcst>594000</fcst>
    <fcst>597600</fcst>
    <fcst>601200</fcst>
    <fcst>604800</fcst>
    <fcst>608400</fcst>
    <fcst>612000</fcst>
    <fcst>615600</fcst>
    <fcst>619200</fcst>
    <fcst>622800</fcst>
    <fcst>626400</fcst>
    <fcst>630000</fcst>
    <fcst>633600</fcst>
    <fcst>637200</fcst>
    <fcst>640800</fcst>
    <fcst>644400</fcst>
    <fcst>648000</fcst>
    <fcst>651600</fcst>
    <fcst>655200</fcst>
    <fcst>658800</fcst>
    <fcst>662400</fcst>
    <fcst>666000</fcst>
    <fcst>669600</fcst>
    <fcst>673200</fcst>
    <fcst>676800</fcst>
    <fcst>680400</fcst>
    <fcst>684000</fcst>
    <fcst>687600</fcst>
    <fcst>691200</fcst>
    <fcst>694800</fcst>
    <fcst>698400</fcst>
    <fcst>702000</fcst>
    <fcst>705600</fcst>
    <fcst>709200</fcst>
    <fcst>712800</fcst>
    <fcst>716400</fcst>
    <fcst>720000</fcst>
    <fcst>723600</fcst>
    <fcst>727200</fcst>
    <fcst>730800</fcst>
    <fcst>734400</fcst>
    <fcst>738000</fcst>
    <fcst>741600</fcst>
    <fcst>745200</fcst>
    <fcst>748800</fcst>
    <fcst>752400</fcst>
    <fcst>756000</fcst>
    <fcst>759600</fcst>
    <fcst>763200</fcst>
    <fcst>766800</fcst>
    <fcst>770400</fcst>
    <fcst>774000</fcst>
    <fcst>777600</fcst>
    <fcst>781200</fcst>
    <fcst>784800</fcst>
    <fcst>788400</fcst>
    <fcst>792000</fcst>
    <fcst>795600</fcst>
    <fcst>799200</fcst>
    <fcst>802800</fcst>
    <fcst>806400</fcst>
    <fcst>810000</fcst>
    <fcst>813600</fcst>
    <fcst>817200</fcst>
    <fcst>820800</fcst>
    <fcst>824400</fcst>
    <fcst>828000</fcst>
    <fcst>831600</fcst>
    <fcst>835200</fcst>
    <fcst>838800</fcst>
    <fcst>842400</fcst>
    <fcst>846000</fcst>
    <fcst>849600</fcst>
    <fcst>853200</fcst>
    <fcst>856800</fcst>
    <fcst>860400</fcst>
    <fcst>864000</fcst>
    <fcst>867600</fcst>
    <fcst>871200</fcst>
    <fcst>874800</fcst>
    <fcst>878400</fcst>
    <fcst>882000</fcst>
    <fcst>885600</fcst>
    <fcst>889200</fcst>
    <fcst>892800</fcst>
    <fcst>896400</fcst>
    <fcst>900000</fcst>
    <fcst>903600</fcst>
    <fcst>907200</fcst>
    <fcst>910800</fcst>
    <fcst>914400</fcst>
    <fcst>918000</fcst>
    <fcst>921600</fcst>
    <fcst>925200</fcst>
    <fcst>928800</fcst>
    <fcst>932400</fcst>
    <fcst>936000</fcst>
    <fcst>939600</fcst>
    <fcst>943200</fcst>
    <fcst>946800</fcst>
    <fcst>950400</fcst>
    <fcst>957600</fcst>
    <fcst>961200</fcst>
    <fcst>964800</fcst>
    <fcst>968400</fcst>
    <fcst>972000</fcst>
    <fcst>975600</fcst>
    <fcst>979200</fcst>
    <fcst>982800</fcst>
    <fcst>986400</fcst>
    <fcst>990000</fcst>
    <fcst>993600</fcst>
  </valtimeMINUSreftime>
  <gridParameterInfo xmlns:xsi="http://www.w3.org/2001/XMLSchema-instance" xsi:type="parameterInfo">
    <short_name>mnt</short_name>
    <long_name>Minimum Temperature</long_name>
    <units>K</units>
    <udunits>degree_Kelvin</udunits>
    <uiname>minT</uiname>
    <valid_range>180.0</valid_range>
    <valid_range>330.0</valid_range>
    <fillValue>-99999.0</fillValue>
    <n3D>1</n3D>
    <levelsDesc>FHAG 2</levelsDesc>
    <levels>
      <level>FHAG2</level>
    </levels>
  </gridParameterInfo>
  <gridParameterInfo xmlns:xsi="http://www.w3.org/2001/XMLSchema-instance" xsi:type="parameterInfo">
    <useDatabaseTimeRange>true</useDatabaseTimeRange>
    <short_name>MINRH12hr</short_name>
    <long_name>Minimum 12-H RH</long_name>
    <units>%</units>
    <udunits>degree_Kelvin</udunits>
    <uiname>MINRH12hr</uiname>
    <valid_range>0.0</valid_range>
    <valid_range>100.0</valid_range>
    <fillValue>-99999.0</fillValue>
    <n3D>1</n3D>
    <levelsDesc>FHAG 2</levelsDesc>
    <levels>
      <level>FHAG2</level>
    </levels>
  </gridParameterInfo>
  <gridParameterInfo xmlns:xsi="http://www.w3.org/2001/XMLSchema-instance" xsi:type="parameterInfo">
    <useDatabaseTimeRange>true</useDatabaseTimeRange>
    <short_name>MAXRH12hr</short_name>
    <long_name>Maximum 12-H RH</long_name>
    <units>%</units>
    <udunits>degree_Kelvin</udunits>
    <uiname>MAXRH12hr</uiname>
    <valid_range>0.0</valid_range>
    <valid_range>100.0</valid_range>
    <fillValue>-99999.0</fillValue>
    <n3D>1</n3D>
    <levelsDesc>FHAG 2</levelsDesc>
    <levels>
      <level>FHAG2</level>
    </levels>
  </gridParameterInfo>
  <gridParameterInfo xmlns:xsi="http://www.w3.org/2001/XMLSchema-instance" xsi:type="parameterInfo">
    <short_name>tp</short_name>
    <long_name>6-hr total precipitation</long_name>
    <units>mm</units>
    <udunits>millimeter</udunits>
    <uiname>QPF</uiname>
    <valid_range>0.0</valid_range>
    <valid_range>1000.0</valid_range>
    <fillValue>-99999.0</fillValue>
    <n3D>0</n3D>
    <levelsDesc>SFC</levelsDesc>
    <levels>
      <level>SFC</level>
    </levels>
  </gridParameterInfo>
  <gridParameterInfo xmlns:xsi="http://www.w3.org/2001/XMLSchema-instance" xsi:type="parameterInfo">
    <short_name>staticSpacing</short_name>
    <long_name>Grid spacing</long_name>
    <units>meters</units>
    <fillValue>-99999.0</fillValue>
  </gridParameterInfo>
  <gridParameterInfo xmlns:xsi="http://www.w3.org/2001/XMLSchema-instance" xsi:type="parameterInfo">
    <short_name>vis</short_name>
    <long_name>visibility</long_name>
    <units>m</units>
    <udunits>meter</udunits>
    <uiname>visibility</uiname>
    <valid_range>0.0</valid_range>
    <valid_range>100000.0</valid_range>
    <fillValue>-99999.0</fillValue>
    <n3D>1</n3D>
    <levelsDesc>SFC</levelsDesc>
    <levels>
         <level>SFC</level>
    </levels>
  </gridParameterInfo>
  <gridParameterInfo xmlns:xsi="http://www.w3.org/2001/XMLSchema-instance" xsi:type="parameterInfo">
    <short_name>cc</short_name>
    <long_name>Cloud Ceiling</long_name>
    <units>m</units>
    <udunits>meters</udunits>
    <uiname>cloudCeiling</uiname>
    <valid_range>-2000.0</valid_range>
    <valid_range>30000.0</valid_range>
    <fillValue>-99999.0</fillValue>
    <n3D>0</n3D>
    <levelsDesc>CLG CBL</levelsDesc>
    <levels>
         <level>CLG</level>
         <level>CBL</level>
    </levels>
  </gridParameterInfo>
  <gridParameterInfo xmlns:xsi="http://www.w3.org/2001/XMLSchema-instance" xsi:type="parameterInfo">
    <short_name>vis</short_name>
    <long_name>visibility</long_name>
    <units>m</units>
    <udunits>meter</udunits>
    <uiname>visibility</uiname>
    <valid_range>0.0</valid_range>
    <valid_range>100000.0</valid_range>
    <fillValue>-99999.0</fillValue>
    <n3D>1</n3D>
    <levelsDesc>SFC</levelsDesc>
    <levels>
        <level>SFC</level>
    </levels>
  </gridParameterInfo>
  <gridParameterInfo xmlns:xsi="http://www.w3.org/2001/XMLSchema-instance" xsi:type="parameterInfo">
    <short_name>pop</short_name>
    <long_name>Probability of Precip</long_name>
    <units>%</units>
    <udunits>percent</udunits>
    <uiname>PcpProb</uiname>
    <valid_range>0.0</valid_range>
    <valid_range>100.0</valid_range>
    <fillValue>-99999.0</fillValue>
    <n3D>0</n3D>
    <levelsDesc>SFC</levelsDesc>
    <levels>
      <level>SFC</level>
    </levels>
  </gridParameterInfo>
  <gridParameterInfo xmlns:xsi="http://www.w3.org/2001/XMLSchema-instance" xsi:type="parameterInfo">
    <short_name>pop12hr</short_name>
    <long_name>Probability of 12hr precip</long_name>
    <units>%</units>
    <udunits>percent</udunits>
    <uiname>12hrPcpProb</uiname>
    <valid_range>0.0</valid_range>
    <valid_range>100.0</valid_range>
    <fillValue>-99999.0</fillValue>
    <n3D>0</n3D>
    <levelsDesc>SFC</levelsDesc>
    <levels>
      <level>SFC</level>
    </levels>
  </gridParameterInfo>
  <gridParameterInfo xmlns:xsi="http://www.w3.org/2001/XMLSchema-instance" xsi:type="parameterInfo">
    <short_name>pop6hr</short_name>
    <long_name>Probability of 6hr precip</long_name>
    <units>%</units>
    <udunits>percent</udunits>
    <uiname>6hrPcpProb</uiname>
    <valid_range>0.0</valid_range>
    <valid_range>100.0</valid_range>
    <fillValue>-99999.0</fillValue>
    <n3D>0</n3D>
    <levelsDesc>SFC</levelsDesc>
    <levels>
      <level>SFC</level>
    </levels>
  </gridParameterInfo>
  <gridParameterInfo xmlns:xsi="http://www.w3.org/2001/XMLSchema-instance" xsi:type="parameterInfo">
    <short_name>pop1hr</short_name>
    <long_name>Probability of 1hr precip</long_name>
    <units>%</units>
    <udunits>percent</udunits>
    <uiname>1hrPcpProb</uiname>
    <valid_range>0.0</valid_range>
    <valid_range>100.0</valid_range>
    <fillValue>-99999.0</fillValue>
    <n3D>0</n3D>
    <levelsDesc>SFC</levelsDesc>
    <levels>
      <level>SFC</level>
    </levels>
  </gridParameterInfo>
  <gridParameterInfo xmlns:xsi="http://www.w3.org/2001/XMLSchema-instance" xsi:type="parameterInfo">
    <short_name>ppi6hr</short_name>
    <long_name>6HR PPI</long_name>
    <units>1ndex</units>
    <udunits>index</udunits>
    <uiname>PPI6hr</uiname>
    <valid_range>0.0</valid_range>
    <valid_range>100.0</valid_range>
    <fillValue>-99999.0</fillValue>
    <n3D>0</n3D>
    <levelsDesc>SFC</levelsDesc>
    <levels>
      <level>SFC</level>
    </levels>
  </gridParameterInfo>
  <gridParameterInfo xmlns:xsi="http://www.w3.org/2001/XMLSchema-instance" xsi:type="parameterInfo">
    <short_name>tcc</short_name>
    <long_name>Total Cloud Cover</long_name>
    <units>%</units>
    <udunits>percent</udunits>
    <uiname>totalCldCvr</uiname>
    <valid_range>0.0</valid_range>
    <valid_range>100.0</valid_range>
    <fillValue>-99999.0</fillValue>
    <n3D>0</n3D>
    <levelsDesc>SFC</levelsDesc>
    <levels>
      <level>SFC</level>
    </levels>
  </gridParameterInfo>
  <gridParameterInfo xmlns:xsi="http://www.w3.org/2001/XMLSchema-instance" xsi:type="parameterInfo">
    <short_name>thp12hr</short_name>
    <long_name>12hr Thunderstorm Probability</long_name>
    <units>%</units>
    <udunits>percent</udunits>
    <uiname>12hrTstrmProb</uiname>
    <valid_range>0.0</valid_range>
    <valid_range>100.0</valid_range>
    <fillValue>-99999.0</fillValue>
    <n3D>0</n3D>
    <levelsDesc>SFC</levelsDesc>
    <levels>
      <level>SFC</level>
    </levels>
  </gridParameterInfo>
  <gridParameterInfo xmlns:xsi="http://www.w3.org/2001/XMLSchema-instance" xsi:type="parameterInfo">
    <short_name>rh</short_name>
    <long_name>Relative Humidity</long_name>
    <units>%</units>
    <udunits>percent</udunits>
    <uiname>rh</uiname>
    <valid_range>0.0</valid_range>
    <valid_range>100.0</valid_range>
    <fillValue>-99999.0</fillValue>
    <n3D>1</n3D>
    <levelsDesc>FHAG 2</levelsDesc>
    <levels>
      <level>FHAG2</level>
    </levels>
  </gridParameterInfo>
  <gridParameterInfo xmlns:xsi="http://www.w3.org/2001/XMLSchema-instance" xsi:type="parameterInfo">
    <short_name>wd</short_name>
    <long_name>Wind Direction</long_name>
    <units>degreeTrue</units>
    <udunits>degree_True</udunits>
    <uiname>WD</uiname>
    <valid_range>0.0</valid_range>
    <valid_range>360.0</valid_range>
    <fillValue>-99999.0</fillValue>
    <n3D>1</n3D>
    <levelsDesc>FHAG 10, FHAG 0-610</levelsDesc>
    <levels>
      <level>FHAG10</level>
      <level>FHAG0610</level>
    </levels>
  </gridParameterInfo>
  <gridParameterInfo xmlns:xsi="http://www.w3.org/2001/XMLSchema-instance" xsi:type="parameterInfo">
    <short_name>wgs</short_name>
    <long_name>Wind Gust Speed</long_name>
    <units>m/s</units>
    <udunits>meter/sec</udunits>
    <uiname>windGustSpeed</uiname>
    <valid_range>-150.0</valid_range>
    <valid_range>150.0</valid_range>
    <fillValue>-99999.0</fillValue>
    <n3D>1</n3D>
    <levelsDesc>FHAG 10</levelsDesc>
    <levels>
      <level>FHAG10</level>
    </levels>
  </gridParameterInfo>
  <gridParameterInfo xmlns:xsi="http://www.w3.org/2001/XMLSchema-instance" xsi:type="parameterInfo">
    <short_name>mxt</short_name>
    <long_name>Maximum Temperature</long_name>
    <units>K</units>
    <udunits>degree_Kelvin</udunits>
    <uiname>maxT</uiname>
    <valid_range>180.0</valid_range>
    <valid_range>330.0</valid_range>
    <fillValue>-99999.0</fillValue>
    <n3D>1</n3D>
    <levelsDesc>FHAG 2</levelsDesc>
    <levels>
      <level>FHAG2</level>
    </levels>
  </gridParameterInfo>
  <gridParameterInfo xmlns:xsi="http://www.w3.org/2001/XMLSchema-instance" xsi:type="parameterInfo">
    <short_name>thp6hr</short_name>
    <long_name>6hr Thunderstorm Probability</long_name>
    <units>%</units>
    <udunits>percent</udunits>
    <uiname>6hrTstrmProb</uiname>
    <valid_range>0.0</valid_range>
    <valid_range>100.0</valid_range>
    <fillValue>-99999.0</fillValue>
    <n3D>0</n3D>
    <levelsDesc>SFC</levelsDesc>
    <levels>
      <level>SFC</level>
    </levels>
  </gridParameterInfo>
  <gridParameterInfo xmlns:xsi="http://www.w3.org/2001/XMLSchema-instance" xsi:type="parameterInfo">
    <short_name>staticCoriolis</short_name>
    <long_name>Coriolis parameter</long_name>
    <units>/s</units>
    <fillValue>-99999.0</fillValue>
  </gridParameterInfo>
  <gridParameterInfo xmlns:xsi="http://www.w3.org/2001/XMLSchema-instance" xsi:type="parameterInfo">
    <short_name>dpt</short_name>
    <long_name>Dewpoint Temperature</long_name>
    <units>K</units>
    <udunits>degree_Kelvin</udunits>
    <uiname>Td</uiname>
    <valid_range>180.0</valid_range>
    <valid_range>330.0</valid_range>
    <fillValue>-99999.0</fillValue>
    <n3D>1</n3D>
    <levelsDesc>FHAG 2 SFC</levelsDesc>
    <levels>
      <level>SFC</level>
      <level>FHAG2</level>
    </levels>
  </gridParameterInfo>
  <gridParameterInfo xmlns:xsi="http://www.w3.org/2001/XMLSchema-instance" xsi:type="parameterInfo">
    <short_name>ws</short_name>
    <long_name>Wind Speed</long_name>
    <units>m/s</units>
    <udunits>meter/sec</udunits>
    <uiname>WS</uiname>
    <valid_range>-150.0</valid_range>
    <valid_range>150.0</valid_range>
    <fillValue>-99999.0</fillValue>
    <n3D>1</n3D>
    <levelsDesc>FHAG 10, FHAG 0-610, FHAG 30, FHAG 80</levelsDesc>
    <levels>
      <level>FHAG10</level>
      <level>FHAG0610</level>
      <level>FHAG30</level>
      <level>FHAG80</level>
    </levels>
  </gridParameterInfo>
  <gridParameterInfo xmlns:xsi="http://www.w3.org/2001/XMLSchema-instance" xsi:type="parameterInfo">
    <short_name>tp1hr</short_name>
    <long_name>1-hr total precipitation</long_name>
    <units>mm</units>
    <udunits>millimeter</udunits>
    <uiname>1hrtotPrecip</uiname>
    <valid_range>0.0</valid_range>
    <valid_range>1000.0</valid_range>
    <fillValue>-99999.0</fillValue>
    <n3D>0</n3D>
    <levelsDesc>SFC</levelsDesc>
    <levels>
      <level>SFC</level>
    </levels>
  </gridParameterInfo>
  <gridParameterInfo xmlns:xsi="http://www.w3.org/2001/XMLSchema-instance" xsi:type="parameterInfo">
    <short_name>tp6hr</short_name>
    <long_name>6-hr total precipitation</long_name>
    <units>mm</units>
    <udunits>millimeter</udunits>
    <uiname>6hrtotPrecip</uiname>
    <valid_range>0.0</valid_range>
    <valid_range>1000.0</valid_range>
    <fillValue>-99999.0</fillValue>
    <n3D>0</n3D>
    <levelsDesc>SFC</levelsDesc>
    <levels>
      <level>SFC</level>
    </levels>
  </gridParameterInfo>
  <gridParameterInfo xmlns:xsi="http://www.w3.org/2001/XMLSchema-instance" xsi:type="parameterInfo">
    <short_name>tp12hr</short_name>
    <long_name>12-hr total precipitation</long_name>
    <units>mm</units>
    <udunits>millimeter</udunits>
    <uiname>12hrtotPrecip</uiname>
    <valid_range>0.0</valid_range>
    <valid_range>1000.0</valid_range>
    <fillValue>-99999.0</fillValue>
    <n3D>0</n3D>
    <levelsDesc>SFC</levelsDesc>
    <levels>
      <level>SFC</level>
    </levels>
  </gridParameterInfo>
  <gridParameterInfo xmlns:xsi="http://www.w3.org/2001/XMLSchema-instance" xsi:type="parameterInfo">
    <short_name>thp3hr</short_name>
    <long_name>3hr Thunderstorm Probability</long_name>
    <units>%</units>
    <udunits>percent</udunits>
    <uiname>3hrTstrmProb</uiname>
    <valid_range>0.0</valid_range>
    <valid_range>100.0</valid_range>
    <fillValue>-99999.0</fillValue>
    <n3D>0</n3D>
    <levelsDesc>SFC</levelsDesc>
    <levels>
      <level>SFC</level>
    </levels>
  </gridParameterInfo>
  <gridParameterInfo xmlns:xsi="http://www.w3.org/2001/XMLSchema-instance" xsi:type="parameterInfo">
    <short_name>t</short_name>
    <long_name>temperature</long_name>
    <units>K</units>
    <udunits>degree_Kelvin</udunits>
    <uiname>T</uiname>
    <valid_range>180.0</valid_range>
    <valid_range>330.0</valid_range>
    <fillValue>-99999.0</fillValue>
    <n3D>1</n3D>
    <levelsDesc>FHAG 2</levelsDesc>
    <levels>
      <level>FHAG2</level>
    </levels>
  </gridParameterInfo>
  <gridParameterInfo xmlns:xsi="http://www.w3.org/2001/XMLSchema-instance" xsi:type="parameterInfo">
    <short_name>snowlvl</short_name>
    <long_name>Snow Level</long_name>
    <units>m</units>
    <udunits>meters</udunits>
    <uiname>SnowLvl</uiname>
    <valid_range>0.0</valid_range>
    <valid_range>6000.0</valid_range>
    <fillValue>-99999.0</fillValue>
    <n3D>0</n3D>
    <levelsDesc>FH 0</levelsDesc>
    <levels>
      <level>FH0</level>
    </levels>
  </gridParameterInfo>
  <gridParameterInfo xmlns:xsi="http://www.w3.org/2001/XMLSchema-instance" xsi:type="parameterInfo">
       <short_name>tmean</short_name>
       <long_name>temperature mean</long_name>
       <units>K</units>
       <udunits>degree_Kelvin</udunits>
       <uiname>Tmean</uiname>
       <valid_range>180.0</valid_range>
       <valid_range>330.0</valid_range>
       <fillValue>-99999.0</fillValue>
       <n3D>0</n3D>
       <levelsDesc>FHAG 2</levelsDesc>
       <levels>
         <level>FHAG2</level>
       </levels>
  </gridParameterInfo>
  <gridParameterInfo xmlns:xsi="http://www.w3.org/2001/XMLSchema-instance" xsi:type="parameterInfo">
       <short_name>dptmean</short_name>
       <long_name>dew point temperature mean</long_name>
       <units>K</units>
       <udunits>degree_Kelvin</udunits>
       <uiname>DpTmean</uiname>
       <valid_range>180.0</valid_range>
       <valid_range>330.0</valid_range>
       <fillValue>-99999.0</fillValue>
       <n3D>0</n3D>
       <levelsDesc>FHAG 2</levelsDesc>
       <levels>
         <level>FHAG2</level>
       </levels>
  </gridParameterInfo>
  <gridParameterInfo xmlns:xsi="http://www.w3.org/2001/XMLSchema-instance" xsi:type="parameterInfo">
       <short_name>maxtw</short_name>
       <long_name>Max Wetbulb Aloft</long_name>
       <units>K</units>
       <udunits>degree_Kelvin</udunits>
       <uiname>MaxTW</uiname>
       <valid_range>180.0</valid_range>
       <valid_range>330.0</valid_range>
       <fillValue>-99999.0</fillValue>
       <n3D>0</n3D>
       <levelsDesc>FHAG 610-40000</levelsDesc>
       <levels>
         <level>FHAG61040000</level>
       </levels>
  </gridParameterInfo>
  <gridParameterInfo xmlns:xsi="http://www.w3.org/2001/XMLSchema-instance" xsi:type="parameterInfo">
       <short_name>ptyp</short_name>
       <long_name>Precipitation type</long_name>
       <units>1</units>
       <udunits>1</udunits>
       <uiname>pTyp</uiname>
       <valid_range>1.0</valid_range>
       <valid_range>5.0</valid_range>
       <fillValue>-99999.0</fillValue>
       <n3D>0</n3D>
       <levelsDesc>SFC</levelsDesc>
       <levels>
         <level>SFC</level>
       </levels>
  </gridParameterInfo>
  <gridParameterInfo xmlns:xsi="http://www.w3.org/2001/XMLSchema-instance" xsi:type="parameterInfo">
    <short_name>prbcldice</short_name>
    <long_name>Prob Ice Present</long_name>
    <units>%</units>
    <udunits>percent</udunits>
    <uiname>PrbCldIce</uiname>
    <valid_range>0.0</valid_range>
    <valid_range>100.0</valid_range>
    <fillValue>-999999.0</fillValue>
    <n3D>0</n3D>
    <levelsDesc>EA</levelsDesc>
    <levels>
      <level>EA</level>
    </levels>
  </gridParameterInfo>
  <gridParameterInfo xmlns:xsi="http://www.w3.org/2001/XMLSchema-instance" xsi:type="parameterInfo">
    <short_name>ptyperefip</short_name>
    <long_name>Prob ReFreeze Sleet</long_name>
    <units>%</units>
    <udunits>percent</udunits>
    <uiname>PtypeRefip</uiname>
    <valid_range>0.0</valid_range>
    <valid_range>100.0</valid_range>
    <fillValue>-999999.0</fillValue>
    <n3D>0</n3D>
    <levelsDesc>SFC</levelsDesc>
    <levels>
      <level>SFC</level>
    </levels>
  </gridParameterInfo>
  <gridParameterInfo xmlns:xsi="http://www.w3.org/2001/XMLSchema-instance" xsi:type="parameterInfo">
    <short_name>ptypfreezingrain</short_name>
    <long_name>Prob Precip Type is Freezing Rain</long_name>
    <units>%</units>
    <udunits>percent</udunits>
    <uiname>PTypFreezingRain</uiname>
    <valid_range>0.0</valid_range>
    <valid_range>100.0</valid_range>
    <fillValue>-999999.0</fillValue>
    <n3D>0</n3D>
    <levelsDesc>SFC</levelsDesc>
    <levels>
      <level>SFC</level>
    </levels>
  </gridParameterInfo>
  <gridParameterInfo xmlns:xsi="http://www.w3.org/2001/XMLSchema-instance" xsi:type="parameterInfo">
    <short_name>ptyprain</short_name>
    <long_name>Prob Precip Type is Rain</long_name>
    <units>%</units>
    <udunits>percent</udunits>
    <uiname>PTypRain</uiname>
    <valid_range>0.0</valid_range>
    <valid_range>100.0</valid_range>
    <fillValue>-999999.0</fillValue>
    <n3D>0</n3D>
    <levelsDesc>SFC</levelsDesc>
    <levels>
      <level>SFC</level>
    </levels>
  </gridParameterInfo>
  <gridParameterInfo xmlns:xsi="http://www.w3.org/2001/XMLSchema-instance" xsi:type="parameterInfo">
    <short_name>ptypsnow</short_name>
    <long_name>Prob Precip Type is Snow</long_name>
    <units>%</units>
    <udunits>percent</udunits>
    <uiname>PTypSnow</uiname>
    <valid_range>0.0</valid_range>
    <valid_range>100.0</valid_range>
    <fillValue>-999999.0</fillValue>
    <n3D>0</n3D>
    <levelsDesc>SFC</levelsDesc>
    <levels>
      <level>SFC</level>
    </levels>
  </gridParameterInfo>
  <gridParameterInfo xmlns:xsi="http://www.w3.org/2001/XMLSchema-instance" xsi:type="parameterInfo">
    <short_name>ptypicepellets</short_name>
    <long_name>Prob Precip Type is Ice Pellets</long_name>
    <units>%</units>
    <udunits>percent</udunits>
    <uiname>PTypIcePellets</uiname>
    <valid_range>0.0</valid_range>
    <valid_range>100.0</valid_range>
    <fillValue>-999999.0</fillValue>
    <n3D>0</n3D>
    <levelsDesc>SFC</levelsDesc>
    <levels>
      <level>SFC</level>
    </levels>
  </gridParameterInfo>
  <gridParameterInfo xmlns:xsi="http://www.w3.org/2001/XMLSchema-instance" xsi:type="parameterInfo">
    <short_name>pbe</short_name>
    <long_name>Positive Bouyant Energy</long_name>
    <units>J/kg</units>
    <udunits>joule/Kilogram</udunits>
    <uiname>PBE</uiname>
    <valid_range>0.0</valid_range>
    <valid_range>6000.0</valid_range>
    <fillValue>-99999.0</fillValue>
    <n3D>1</n3D>
    <levelsDesc>FHAG 610-40000</levelsDesc>
    <levels>
      <level>FHAG61040000</level>
    </levels>
  </gridParameterInfo>
  <gridParameterInfo xmlns:xsi="http://www.w3.org/2001/XMLSchema-instance" xsi:type="parameterInfo">
    <short_name>nbe</short_name>
    <long_name>Negative Bouyant Energy</long_name>
    <units>J/kg</units>
    <udunits>joule/Kilogram</udunits>
    <uiname>NBE</uiname>
    <valid_range>0.0</valid_range>
    <valid_range>6000.0</valid_range>
    <fillValue>-99999.0</fillValue>
    <n3D>1</n3D>
    <levelsDesc>SFC</levelsDesc>
    <levels>
      <level>SFC</level>
    </levels>
  </gridParameterInfo>
  <gridParameterInfo xmlns:xsi="http://www.w3.org/2001/XMLSchema-instance" xsi:type="parameterInfo">
    <short_name>snowratio</short_name>
    <long_name>Snow Ratio</long_name>
    <units>in</units>
    <udunits>in</udunits>
    <uiname>snowratio</uiname>
    <valid_range>0.0</valid_range>
    <valid_range>40.0</valid_range>
    <fillValue>-99999.0</fillValue>
    <n3D>0</n3D>
    <levelsDesc>SFC</levelsDesc>
    <levels>
      <level>SFC</level>
    </levels>
  </gridParameterInfo>
    <gridParameterInfo xmlns:xsi="http://www.w3.org/2001/XMLSchema-instance" xsi:type="parameterInfo">
    <short_name>mixht</short_name>
    <long_name>Mixing Height</long_name>
    <units>m</units>
    <udunits>meters</udunits>
    <uiname>MIXHT</uiname>
    <valid_range>0.0</valid_range>
    <valid_range>3689.0</valid_range>
    <fillValue>-999999.0</fillValue>
    <n3D>0</n3D>
    <levelsDesc>EA</levelsDesc>
    <levels>
      <level>EA</level>
    </levels>
  </gridParameterInfo>
  <gridParameterInfo xmlns:xsi="http://www.w3.org/2001/XMLSchema-instance" xsi:type="parameterInfo">
    <short_name>tpwdir</short_name>
    <long_name>Tropical Wind direction</long_name>
    <units>deg</units>
    <udunits>degrees</udunits>
    <uiname>TPWDIR</uiname>
    <valid_range>0.0</valid_range>
    <valid_range>360.0</valid_range>
    <fillValue>-99999.0</fillValue>
    <n3D>1</n3D>
    <levelsDesc>FHAG 10</levelsDesc>
    <levels>
      <level>FHAG10</level>
    </levels>
  </gridParameterInfo>
  <gridParameterInfo xsi:type="parameterInfo" xmlns:xsi="http://www.w3.org/2001/XMLSchema-instance">
    <short_name>tpwspd</short_name>
    <long_name>Tropical Wind Speed</long_name>
    <units>m/s</units>
    <udunits>meter/sec</udunits>
    <uiname>TPWSPD</uiname>
    <valid_range>0.0</valid_range>
    <valid_range>65.0</valid_range>
    <fillValue>-999999.0</fillValue>
    <n3D>1</n3D>
    <levelsDesc>FHAG 10</levelsDesc>
    <levels>
      <level>FHAG10</level>
    </levels>
  </gridParameterInfo>
  <gridParameterInfo xmlns:xsi="http://www.w3.org/2001/XMLSchema-instance" xsi:type="parameterInfo">
    <short_name>trwdir</short_name>
    <long_name>Transport Wind direction</long_name>
    <units>deg</units>
    <udunits>degrees</udunits>
    <uiname>TRWDIR</uiname>
    <valid_range>0.0</valid_range>
    <valid_range>360.0</valid_range>
    <fillValue>-99999.0</fillValue>
    <n3D>1</n3D>
    <levelsDesc>EA</levelsDesc>
    <levels>
      <level>EA</level>
    </levels>
  </gridParameterInfo>
  <gridParameterInfo xsi:type="parameterInfo" xmlns:xsi="http://www.w3.org/2001/XMLSchema-instance">
    <short_name>trwspd</short_name>
    <long_name>Transport Wind Speed</long_name>
    <units>m/s</units>
    <udunits>meter/sec</udunits>
    <uiname>TRWSPD</uiname>
    <valid_range>0.0</valid_range>
    <valid_range>65.0</valid_range>
    <fillValue>-999999.0</fillValue>
    <n3D>1</n3D>
    <levelsDesc>EA</levelsDesc>
    <levels>
      <level>EA</level>
    </levels>
  </gridParameterInfo>
  <gridParameterInfo xsi:type="parameterInfo" xmlns:xsi="http://www.w3.org/2001/XMLSchema-instance">
    <short_name>vrate</short_name>
    <long_name>Ventilation Rate</long_name>
    <units>m^2/s</units>
    <udunits>meter2/sec</udunits>
    <uiname>VRATE</uiname>
    <valid_range>0.0</valid_range>
    <valid_range>49958.0</valid_range>
    <fillValue>-999999.0</fillValue>
    <n3D>1</n3D>
    <levelsDesc>EA</levelsDesc>
    <levels>
      <level>EA</level>
    </levels>
  </gridParameterInfo>
  <gridParameterInfo xsi:type="parameterInfo" xmlns:xsi="http://www.w3.org/2001/XMLSchema-instance">
    <short_name>hindex6hr</short_name>
    <long_name>Haines Index</long_name>
    <units>index</units>
    <udunits>index</udunits>>
    <uiname>HINDEX6hr</uiname>
    <valid_range>2.0</valid_range>
    <valid_range>6.0</valid_range>
    <fillValue>-999999.0</fillValue>
    <n3D>1</n3D>
    <levelsDesc>EA</levelsDesc>
    <levels>
      <level>EA</level>
    </levels>
  </gridParameterInfo>
    <gridParameterInfo xsi:type="parameterInfo" xmlns:xsi="http://www.w3.org/2001/XMLSchema-instance">
    <short_name>fosindx6hr</short_name>
    <long_name>Fosberg Fire Weather Index</long_name>
    <units>index</units>
    <udunits>index</udunits>>
    <uiname>FOSINDX6hr</uiname>
    <valid_range>0.0</valid_range>
    <valid_range>100.0</valid_range>
    <fillValue>-999999.0</fillValue>
    <n3D>1</n3D>
    <levelsDesc>SFC</levelsDesc>
    <levels>
      <level>SFC</level>
    </levels>
  </gridParameterInfo>
  <gridParameterInfo xsi:type="parameterInfo" xmlns:xsi="http://www.w3.org/2001/XMLSchema-instance">
    <short_name>llwshgt</short_name>
    <long_name>LLWS Height</long_name>
    <units>m</units>
    <udunits>meter</udunits>
    <uiname>LLWSHgt</uiname>
    <valid_range>0.0</valid_range>
    <valid_range>609.0</valid_range>
    <fillValue>-999999.0</fillValue>
    <n3D>1</n3D>
    <levelsDesc>FHAG 0-610</levelsDesc>
    <levels>
      <level>FHAG0610</level>
    </levels>
  </gridParameterInfo>
    <gridParameterInfo xsi:type="parameterInfo" xmlns:xsi="http://www.w3.org/2001/XMLSchema-instance">
    <short_name>maxref1hr</short_name>
    <long_name>Simulated Maximum Reflectivity</long_name>
    <units>dBZ</units>
    <udunits>dBZ</udunits>
    <uiname>MAXREF1hr</uiname>
    <valid_range>0.0</valid_range>
    <valid_range>100.0</valid_range>
    <fillValue>-999999.0</fillValue>
    <n3D>1</n3D>
    <levelsDesc>FHAG 1000</levelsDesc>
    <levels>
      <level>FHAG1000</level>
    </levels>
  </gridParameterInfo>
    <gridParameterInfo xsi:type="parameterInfo" xmlns:xsi="http://www.w3.org/2001/XMLSchema-instance">
    <short_name>viliq</short_name>
    <long_name>Vertically Integrated Liquid</long_name>
    <units>kg/m^2</units>
    <udunits>kilogram/meters2</udunits>
    <uiname>VILIQ</uiname>
    <valid_range>0.0</valid_range>
    <valid_range>100.0</valid_range>
    <fillValue>-999999.0</fillValue>
    <n3D>1</n3D>
    <levelsDesc>EA</levelsDesc>
    <levels>
      <level>EA</level>
    </levels>
  </gridParameterInfo>
  <gridParameterInfo xsi:type="parameterInfo" xmlns:xsi="http://www.w3.org/2001/XMLSchema-instance">
    <short_name>retop</short_name>
    <long_name>Echo Tops</long_name>
    <units>m</units>
    <udunits>meter</udunits>
    <uiname>RETOP</uiname>
    <valid_range>1.0</valid_range>
    <valid_range>88888.203</valid_range>
    <fillValue>-999999.0</fillValue>
    <n3D>1</n3D>
    <levelsDesc>CTL</levelsDesc>
    <levels>
      <level>CTL</level>
    </levels>
  </gridParameterInfo>
  <gridParameterInfo xsi:type="parameterInfo" xmlns:xsi="http://www.w3.org/2001/XMLSchema-instance">
    <short_name>wgs50pct</short_name>
    <long_name>10-m Wind Gust</long_name>
    <units>knots</units>
    <udunits>knots</udunits>
    <uiname>WGS50pct</uiname>
    <valid_range>0.0</valid_range>
    <valid_range>100.0</valid_range>
    <fillValue>-999999.0</fillValue>
    <n3D>1</n3D>
    <levelsDesc>FHAG 10</levelsDesc>
    <levels>
      <level>FHAG10</level>
    </levels>
  </gridParameterInfo>
  <gridParameterInfo xsi:type="parameterInfo" xmlns:xsi="http://www.w3.org/2001/XMLSchema-instance">
    <short_name>ws50pct</short_name>
    <long_name>30-m/80-m Wind Speed</long_name>
    <units>m/s</units>
    <udunits>meter/sec</udunits>
    <uiname>WS50pct</uiname>
    <valid_range>0.0</valid_range>
    <valid_range>100.0</valid_range>
    <fillValue>-999999.0</fillValue>
    <n3D>1</n3D>
    <levelsDesc>FHAG 30, 80</levelsDesc>
    <levels>
      <level>FHAG30</level>
      <level>FHAG80</level>
    </levels>
  </gridParameterInfo>
  <gridParameterInfo xsi:type="parameterInfo" xmlns:xsi="http://www.w3.org/2001/XMLSchema-instance">
    <short_name>vis50pct</short_name>
    <long_name>Visibility</long_name>
    <units>m</units>
    <udunits>meter</udunits>
    <uiname>Vis50pct</uiname>
    <valid_range>0.0</valid_range>
    <valid_range>100000.0</valid_range>
    <fillValue>-999999.0</fillValue>
    <n3D>1</n3D>
    <levelsDesc>SFC</levelsDesc>
    <levels>
      <level>SFC</level>
    </levels>
  </gridParameterInfo>
  <gridParameterInfo xsi:type="parameterInfo" xmlns:xsi="http://www.w3.org/2001/XMLSchema-instance">
    <short_name>t50pct</short_name>
    <long_name>Air Temperature</long_name>
    <units>K</units>
    <udunits>degree_Kelvin</udunits>
    <uiname>T50pct</uiname>
    <valid_range>180.0</valid_range>
    <valid_range>330.0</valid_range>
    <fillValue>-999999.0</fillValue>
    <n3D>1</n3D>
    <levelsDesc>FHAG 2</levelsDesc>
    <levels>
      <level>FHAG2</level>
    </levels>
  </gridParameterInfo>
  <gridParameterInfo xsi:type="parameterInfo" xmlns:xsi="http://www.w3.org/2001/XMLSchema-instance">
    <short_name>pmsl10pct</short_name>
    <long_name>10th percentile Mean Sea Level Pressure</long_name>
    <units>Pa</units>
    <udunits>pascal</udunits>
    <uiname>PMSL10pct</uiname>
    <valid_range>80000.0</valid_range>
    <valid_range>110000.0</valid_range>
    <fillValue>-999999.0</fillValue>
    <n3D>1</n3D>
    <levelsDesc>MSL</levelsDesc>
    <levels>
      <level>MSL</level>
    </levels>
  </gridParameterInfo>
  <gridParameterInfo xsi:type="parameterInfo" xmlns:xsi="http://www.w3.org/2001/XMLSchema-instance">
    <short_name>pmsl50pct</short_name>
    <long_name>50th percentile Mean Sea Level Pressure</long_name>
    <units>Pa</units>
    <udunits>pascal</udunits>
    <uiname>PMSL50pct</uiname>
    <valid_range>80000.0</valid_range>
    <valid_range>110000.0</valid_range>
    <fillValue>-999999.0</fillValue>
    <n3D>1</n3D>
    <levelsDesc>MSL</levelsDesc>
    <levels>
      <level>MSL</level>
    </levels>
  </gridParameterInfo>
  <gridParameterInfo xsi:type="parameterInfo" xmlns:xsi="http://www.w3.org/2001/XMLSchema-instance">
    <short_name>pmsl90pct</short_name>
    <long_name>90th percentile Mean Sea Level Pressure</long_name>
    <units>Pa</units>
    <udunits>pascal</udunits>
    <uiname>PMSL90pct</uiname>
    <valid_range>80000.0</valid_range>
    <valid_range>110000.0</valid_range>
    <fillValue>-999999.0</fillValue>
    <n3D>1</n3D>
    <levelsDesc>MSL</levelsDesc>
    <levels>
      <level>MSL</level>
    </levels>
  </gridParameterInfo>
  <gridParameterInfo xsi:type="parameterInfo" xmlns:xsi="http://www.w3.org/2001/XMLSchema-instance">
    <short_name>htsgw</short_name>
    <long_name>Significant Wave Height</long_name>
    <units>m</units>
    <udunits>meter</udunits>
    <uiname>HTSGW</uiname>
    <valid_range>0.0</valid_range>
    <valid_range>50.0</valid_range>
    <fillValue>-999999.0</fillValue>
    <n3D>1</n3D>
    <levelsDesc>SFC</levelsDesc>
    <levels>
      <level>SFC</level>
    </levels>
  </gridParameterInfo>
  <gridParameterInfo xsi:type="parameterInfo" xmlns:xsi="http://www.w3.org/2001/XMLSchema-instance">
    <short_name>pwther</short_name>
    <long_name>Predominant Weather</long_name>
    <units>Numeric</units>
    <udunits>Numeric</udunits>
    <uiname>PWTHER</uiname>
    <valid_range>0.0</valid_range>
    <valid_range>138.0</valid_range>
    <fillValue>-999999.0</fillValue>
    <n3D>1</n3D>
    <levelsDesc>SFC</levelsDesc>
    <levels>
      <level>SFC</level>
    </levels>
  </gridParameterInfo>
  <gridParameterInfo xsi:type="parameterInfo" xmlns:xsi="http://www.w3.org/2001/XMLSchema-instance">
    <short_name>totsn1hr</short_name>
    <long_name>1-h Snow Accumulation</long_name>
    <units>m</units>
    <udunits>meter</udunits>
    <uiname>TOTSN1hr</uiname>
    <valid_range>0.0</valid_range>
    <valid_range>3.78</valid_range>
    <fillValue>-999999.0</fillValue>
    <n3D>1</n3D>
    <levelsDesc>SFC</levelsDesc>
    <levels>
      <level>SFC</level>
    </levels>
  </gridParameterInfo>
  <gridParameterInfo xsi:type="parameterInfo" xmlns:xsi="http://www.w3.org/2001/XMLSchema-instance">
    <short_name>ficeac1hr</short_name>
    <long_name>1-h Ice Accumulation</long_name>
    <units>m</units>
    <udunits>meter</udunits>
    <uiname>FICEAC1hr</uiname>
    <valid_range>0.0</valid_range>
    <valid_range>15</valid_range>
    <fillValue>-999999.0</fillValue>
    <n3D>1</n3D>
    <levelsDesc>SFC</levelsDesc>
    <levels>
      <level>SFC</level>
    </levels>
  </gridParameterInfo>
  <gridParameterInfo xsi:type="parameterInfo" xmlns:xsi="http://www.w3.org/2001/XMLSchema-instance">
    <short_name>totsn6hr</short_name>
    <long_name>6-h Snow Accumulation</long_name>
    <units>m</units>
    <udunits>meter</udunits>
    <uiname>TOTSN6hr</uiname>
    <valid_range>0.0</valid_range>
    <valid_range>1000.0</valid_range>
    <fillValue>-999999.0</fillValue>
    <n3D>1</n3D>
    <levelsDesc>SFC</levelsDesc>
    <levels>
      <level>SFC</level>
    </levels>
  </gridParameterInfo>
  <gridParameterInfo xsi:type="parameterInfo" xmlns:xsi="http://www.w3.org/2001/XMLSchema-instance">
    <short_name>ficeac6hr</short_name>
    <long_name>6-h Ice Accumulation</long_name>
    <units>m</units>
    <udunits>meter</udunits>
    <uiname>FICEAC6hr</uiname>
    <valid_range>0.0</valid_range>
    <valid_range>15.0</valid_range>
    <fillValue>-999999.0</fillValue>
    <n3D>1</n3D>
    <levelsDesc>SFC</levelsDesc>
    <levels>
      <level>SFC</level>
    </levels>
  </gridParameterInfo>
  <gridParameterInfo xsi:type="parameterInfo" xmlns:xsi="http://www.w3.org/2001/XMLSchema-instance">
    <short_name>ppi1hr</short_name>
    <long_name>1-h Precipitation Potential Index</long_name>
    <units>%</units>
    <udunits>percent</udunits>
    <uiname>PPI1hr</uiname>
    <valid_range>0.0</valid_range>
    <valid_range>100.0</valid_range>
    <fillValue>-999999.0</fillValue>
    <n3D>1</n3D>
    <levelsDesc>SFC</levelsDesc>
    <levels>
      <level>SFC</level>
    </levels>
  </gridParameterInfo>
  <gridParameterInfo xsi:type="parameterInfo" xmlns:xsi="http://www.w3.org/2001/XMLSchema-instance">
    <short_name>thp1hr</short_name>
    <long_name>1-h SREF-based Prob. of a Thunderstorm</long_name>
    <units>%</units>
    <udunits>percent</udunits>
    <uiname>ThP1hr</uiname>
    <valid_range>0.0</valid_range>
    <valid_range>100.0</valid_range>
    <fillValue>-999999.0</fillValue>
    <n3D>1</n3D>
    <levelsDesc>SFC</levelsDesc>
    <levels>
      <level>SFC</level>
    </levels>
  </gridParameterInfo>
  <gridParameterInfo xsi:type="parameterInfo" xmlns:xsi="http://www.w3.org/2001/XMLSchema-instance">
    <short_name>drytpprob3hr</short_name>
    <long_name>3-h SREF-based Prob. of a Dry Thunderstorm</long_name>
    <units>%</units>
    <udunits>percent</udunits>
    <uiname>DRYTPPROB3hr</uiname>
    <valid_range>0.0</valid_range>
    <valid_range>100.0</valid_range>
    <fillValue>-999999.0</fillValue>
    <n3D>1</n3D>
    <levelsDesc>SFC</levelsDesc>
    <levels>
      <level>SFC</level>
    </levels>
  </gridParameterInfo>
  <gridParameterInfo xsi:type="parameterInfo" xmlns:xsi="http://www.w3.org/2001/XMLSchema-instance">
    <short_name>tp10pct6hr</short_name>
    <long_name>10th percentile 6hr Quant</long_name>
    <units>millimeter</units>
    <udunits>mm</udunits>
    <uiname>TP10pct6hr</uiname>
    <valid_range>0.0</valid_range>
    <valid_range>1000.0</valid_range>
    <fillValue>-999999.0</fillValue>
    <n3D>1</n3D>
    <levelsDesc>SFC</levelsDesc>
    <levels>
      <level>SFC</level>
    </levels>
  </gridParameterInfo>
  <gridParameterInfo xsi:type="parameterInfo" xmlns:xsi="http://www.w3.org/2001/XMLSchema-instance">
    <short_name>tp50pct6hr</short_name>
    <long_name>50th percentile 6hr Quant</long_name>
    <units>millimeter</units>
    <udunits>mm</udunits>
    <uiname>TP50pct6hr</uiname>
    <valid_range>0.0</valid_range>
    <valid_range>1000.0</valid_range>
    <fillValue>-999999.0</fillValue>
    <n3D>1</n3D>
    <levelsDesc>SFC</levelsDesc>
    <levels>
      <level>SFC</level>
    </levels>
  </gridParameterInfo>
  <gridParameterInfo xsi:type="parameterInfo" xmlns:xsi="http://www.w3.org/2001/XMLSchema-instance">
    <short_name>tp90pct6hr</short_name>
    <long_name>90th percentile 6hr Quant</long_name>
    <units>millimeter</units>
    <udunits>mm</udunits>
    <uiname>TP90pct6hr</uiname>
    <valid_range>0.0</valid_range>
    <valid_range>1000.0</valid_range>
    <fillValue>-999999.0</fillValue>
    <n3D>1</n3D>
    <levelsDesc>SFC</levelsDesc>
    <levels>
      <level>SFC</level>
    </levels>
  </gridParameterInfo>
  <gridParameterInfo xsi:type="parameterInfo" xmlns:xsi="http://www.w3.org/2001/XMLSchema-instance">
    <short_name>tp10pct24hr</short_name>
    <long_name>10th percentile 24hr Quant</long_name>
    <units>millimeter</units>
    <udunits>mm</udunits>
    <uiname>TP10pct24hr</uiname>
    <valid_range>0.0</valid_range>
    <valid_range>1000.0</valid_range>
    <fillValue>-999999.0</fillValue>
    <n3D>1</n3D>
    <levelsDesc>SFC</levelsDesc>
    <levels>
      <level>SFC</level>
    </levels>
  </gridParameterInfo>
  <gridParameterInfo xsi:type="parameterInfo" xmlns:xsi="http://www.w3.org/2001/XMLSchema-instance">
    <short_name>tp50pct24hr</short_name>
    <long_name>50th percentile 24hr Quant</long_name>
    <units>millimeter</units>
    <udunits>mm</udunits>
    <uiname>TP50pct24hr</uiname>
    <valid_range>0.0</valid_range>
    <valid_range>1000.0</valid_range>
    <fillValue>-999999.0</fillValue>
    <n3D>1</n3D>
    <levelsDesc>SFC</levelsDesc>
    <levels>
      <level>SFC</level>
    </levels>
  </gridParameterInfo>
  <gridParameterInfo xsi:type="parameterInfo" xmlns:xsi="http://www.w3.org/2001/XMLSchema-instance">
    <short_name>tp90pct24hr</short_name>
    <long_name>90th percentile 24hr Quant</long_name>
    <units>millimeter</units>
    <udunits>mm</udunits>
    <uiname>TP90pct24hr</uiname>
    <valid_range>0.0</valid_range>
    <valid_range>1000.0</valid_range>
    <fillValue>-999999.0</fillValue>
    <n3D>1</n3D>
    <levelsDesc>SFC</levelsDesc>
    <levels>
      <level>SFC</level>
    </levels>
  </gridParameterInfo>
  <gridParameterInfo xsi:type="parameterInfo" xmlns:xsi="http://www.w3.org/2001/XMLSchema-instance">
    <short_name>ficeac5pct24hr</short_name>
    <long_name>5th percentile Flat Ice Accumulation 24 hour</long_name>
    <units>m</units>
    <udunits>meter</udunits>
    <uiname>FICEAC5pct24hr</uiname>
    <valid_range>0.0</valid_range>
    <valid_range>10.0</valid_range>
    <fillValue>-999999.0</fillValue>
    <n3D>1</n3D>
    <levelsDesc>SFC</levelsDesc>
    <levels>
      <level>SFC</level>
    </levels>
  </gridParameterInfo>
  <gridParameterInfo xsi:type="parameterInfo" xmlns:xsi="http://www.w3.org/2001/XMLSchema-instance">
    <short_name>ficeac10pct24hr</short_name>
    <long_name>10th percentile Flat Ice Accumulation 24 hour</long_name>
    <units>m</units>
    <udunits>meter</udunits>
    <uiname>FICEAC10pct24hr</uiname>
    <valid_range>0.0</valid_range>
    <valid_range>10.0</valid_range>
    <fillValue>-999999.0</fillValue>
    <n3D>1</n3D>
    <levelsDesc>SFC</levelsDesc>
    <levels>
      <level>SFC</level>
    </levels>
  </gridParameterInfo>
  <gridParameterInfo xsi:type="parameterInfo" xmlns:xsi="http://www.w3.org/2001/XMLSchema-instance">
    <short_name>ficeac25pct24hr</short_name>
    <long_name>25th percentile Flat Ice Accumulation 24 hour</long_name>
    <units>m</units>
    <udunits>meter</udunits>
    <uiname>FICEAC25pct24hr</uiname>
    <valid_range>0.0</valid_range>
    <valid_range>10.0</valid_range>
    <fillValue>-999999.0</fillValue>
    <n3D>1</n3D>
    <levelsDesc>SFC</levelsDesc>
    <levels>
      <level>SFC</level>
    </levels>
  </gridParameterInfo>
  <gridParameterInfo xsi:type="parameterInfo" xmlns:xsi="http://www.w3.org/2001/XMLSchema-instance">
    <short_name>ficeac50pct24hr</short_name>
    <long_name>50th percentile Flat Ice Accumulation 24 hour</long_name>
    <units>m</units>
    <udunits>meter</udunits>
    <uiname>FICEAC50pct24hr</uiname>
    <valid_range>0.0</valid_range>
    <valid_range>10.0</valid_range>
    <fillValue>-999999.0</fillValue>
    <n3D>1</n3D>
    <levelsDesc>SFC</levelsDesc>
    <levels>
      <level>SFC</level>
    </levels>
  </gridParameterInfo>
  <gridParameterInfo xsi:type="parameterInfo" xmlns:xsi="http://www.w3.org/2001/XMLSchema-instance">
    <short_name>ficeac75pct24hr</short_name>
    <long_name>75th percentile Flat Ice Accumulation 24 hour</long_name>
    <units>m</units>
    <udunits>meter</udunits>
    <uiname>FICEAC75pct24hr</uiname>
    <valid_range>0.0</valid_range>
    <valid_range>10.0</valid_range>
    <fillValue>-999999.0</fillValue>
    <n3D>1</n3D>
    <levelsDesc>SFC</levelsDesc>
    <levels>
      <level>SFC</level>
    </levels>
  </gridParameterInfo>
  <gridParameterInfo xsi:type="parameterInfo" xmlns:xsi="http://www.w3.org/2001/XMLSchema-instance">
    <short_name>ficeac90pct24hr</short_name>
    <long_name>90th percentile Flat Ice Accumulation 24 hour</long_name>
    <units>m</units>
    <udunits>meter</udunits>
    <uiname>FICEAC90pct24hr</uiname>
    <valid_range>0.0</valid_range>
    <valid_range>10.0</valid_range>
    <fillValue>-999999.0</fillValue>
    <n3D>1</n3D>
    <levelsDesc>SFC</levelsDesc>
    <levels>
      <level>SFC</level>
    </levels>
  </gridParameterInfo>
  <gridParameterInfo xsi:type="parameterInfo" xmlns:xsi="http://www.w3.org/2001/XMLSchema-instance">
    <short_name>ficeac95pct24hr</short_name>
    <long_name>95th percentile Flat Ice Accumulation 24 hour</long_name>
    <units>m</units>
    <udunits>meter</udunits>
    <uiname>FICEAC95pct24hr</uiname>
    <valid_range>0.0</valid_range>
    <valid_range>10.0</valid_range>
    <fillValue>-999999.0</fillValue>
    <n3D>1</n3D>
    <levelsDesc>SFC</levelsDesc>
    <levels>
      <level>SFC</level>
    </levels>
  </gridParameterInfo>
  <gridParameterInfo xsi:type="parameterInfo" xmlns:xsi="http://www.w3.org/2001/XMLSchema-instance">
    <short_name>ficeac5pct48hr</short_name>
    <long_name>5th percentile Flat Ice Accumulation 48 hour</long_name>
    <units>m</units>
    <udunits>meter</udunits>
    <uiname>FICEAC5pct48hr</uiname>
    <valid_range>0.0</valid_range>
    <valid_range>10.0</valid_range>
    <fillValue>-999999.0</fillValue>
    <n3D>1</n3D>
    <levelsDesc>SFC</levelsDesc>
    <levels>
      <level>SFC</level>
    </levels>
  </gridParameterInfo>
  <gridParameterInfo xsi:type="parameterInfo" xmlns:xsi="http://www.w3.org/2001/XMLSchema-instance">
    <short_name>ficeac10pct48hr</short_name>
    <long_name>10th percentile Flat Ice Accumulation 48 hour</long_name>
    <units>m</units>
    <udunits>meter</udunits>
    <uiname>FICEAC10pct48hr</uiname>
    <valid_range>0.0</valid_range>
    <valid_range>10.0</valid_range>
    <fillValue>-999999.0</fillValue>
    <n3D>1</n3D>
    <levelsDesc>SFC</levelsDesc>
    <levels>
      <level>SFC</level>
    </levels>
  </gridParameterInfo>
  <gridParameterInfo xsi:type="parameterInfo" xmlns:xsi="http://www.w3.org/2001/XMLSchema-instance">
    <short_name>ficeac25pct48hr</short_name>
    <long_name>25th percentile Flat Ice Accumulation 48 hour</long_name>
    <units>m</units>
    <udunits>meter</udunits>
    <uiname>FICEAC25pct48hr</uiname>
    <valid_range>0.0</valid_range>
    <valid_range>10.0</valid_range>
    <fillValue>-999999.0</fillValue>
    <n3D>1</n3D>
    <levelsDesc>SFC</levelsDesc>
    <levels>
      <level>SFC</level>
    </levels>
  </gridParameterInfo>
  <gridParameterInfo xsi:type="parameterInfo" xmlns:xsi="http://www.w3.org/2001/XMLSchema-instance">
    <short_name>ficeac50pct48hr</short_name>
    <long_name>50th percentile Flat Ice Accumulation 48 hour</long_name>
    <units>m</units>
    <udunits>meter</udunits>
    <uiname>FICEAC50pct48hr</uiname>
    <valid_range>0.0</valid_range>
    <valid_range>10.0</valid_range>
    <fillValue>-999999.0</fillValue>
    <n3D>1</n3D>
    <levelsDesc>SFC</levelsDesc>
    <levels>
      <level>SFC</level>
    </levels>
  </gridParameterInfo>
  <gridParameterInfo xsi:type="parameterInfo" xmlns:xsi="http://www.w3.org/2001/XMLSchema-instance">
    <short_name>ficeac75pct48hr</short_name>
    <long_name>75th percentile Flat Ice Accumulation 48 hour</long_name>
    <units>m</units>
    <udunits>meter</udunits>
    <uiname>FICEAC75pct48hr</uiname>
    <valid_range>0.0</valid_range>
    <valid_range>10.0</valid_range>
    <fillValue>-999999.0</fillValue>
    <n3D>1</n3D>
    <levelsDesc>SFC</levelsDesc>
    <levels>
      <level>SFC</level>
    </levels>
  </gridParameterInfo>
  <gridParameterInfo xsi:type="parameterInfo" xmlns:xsi="http://www.w3.org/2001/XMLSchema-instance">
    <short_name>ficeac90pct48hr</short_name>
    <long_name>90th percentile Flat Ice Accumulation 48 hour</long_name>
    <units>m</units>
    <udunits>meter</udunits>
    <uiname>FICEAC90pct48hr</uiname>
    <valid_range>0.0</valid_range>
    <valid_range>10.0</valid_range>
    <fillValue>-999999.0</fillValue>
    <n3D>1</n3D>
    <levelsDesc>SFC</levelsDesc>
    <levels>
      <level>SFC</level>
    </levels>
  </gridParameterInfo>
  <gridParameterInfo xsi:type="parameterInfo" xmlns:xsi="http://www.w3.org/2001/XMLSchema-instance">
    <short_name>ficeac95pct48hr</short_name>
    <long_name>95th percentile Flat Ice Accumulation 48 hour</long_name>
    <units>m</units>
    <udunits>meter</udunits>
    <uiname>FICEAC95pct48hr</uiname>
    <valid_range>0.0</valid_range>
    <valid_range>10.0</valid_range>
    <fillValue>-999999.0</fillValue>
    <n3D>1</n3D>
    <levelsDesc>SFC</levelsDesc>
    <levels>
      <level>SFC</level>
    </levels>
  </gridParameterInfo>

  <gridParameterInfo xsi:type="parameterInfo" xmlns:xsi="http://www.w3.org/2001/XMLSchema-instance">
    <short_name>ficeac5pct72hr</short_name>
    <long_name>5th percentile Flat Ice Accumulation 72 hour</long_name>
    <units>m</units>
    <udunits>meter</udunits>
    <uiname>FICEAC5pct72hr</uiname>
    <valid_range>0.0</valid_range>
    <valid_range>10.0</valid_range>
    <fillValue>-999999.0</fillValue>
    <n3D>1</n3D>
    <levelsDesc>SFC</levelsDesc>
    <levels>
      <level>SFC</level>
    </levels>
  </gridParameterInfo>
  <gridParameterInfo xsi:type="parameterInfo" xmlns:xsi="http://www.w3.org/2001/XMLSchema-instance">
    <short_name>ficeac10pct72hr</short_name>
    <long_name>10th percentile Flat Ice Accumulation 72 hour</long_name>
    <units>m</units>
    <udunits>meter</udunits>
    <uiname>FICEAC10pct72hr</uiname>
    <valid_range>0.0</valid_range>
    <valid_range>10.0</valid_range>
    <fillValue>-999999.0</fillValue>
    <n3D>1</n3D>
    <levelsDesc>SFC</levelsDesc>
    <levels>
      <level>SFC</level>
    </levels>
  </gridParameterInfo>
  <gridParameterInfo xsi:type="parameterInfo" xmlns:xsi="http://www.w3.org/2001/XMLSchema-instance">
    <short_name>ficeac25pct72hr</short_name>
    <long_name>25th percentile Flat Ice Accumulation 72 hour</long_name>
    <units>m</units>
    <udunits>meter</udunits>
    <uiname>FICEAC25pct72hr</uiname>
    <valid_range>0.0</valid_range>
    <valid_range>10.0</valid_range>
    <fillValue>-999999.0</fillValue>
    <n3D>1</n3D>
    <levelsDesc>SFC</levelsDesc>
    <levels>
      <level>SFC</level>
    </levels>
  </gridParameterInfo>
  <gridParameterInfo xsi:type="parameterInfo" xmlns:xsi="http://www.w3.org/2001/XMLSchema-instance">
    <short_name>ficeac50pct72hr</short_name>
    <long_name>50th percentile Flat Ice Accumulation 72 hour</long_name>
    <units>m</units>
    <udunits>meter</udunits>
    <uiname>FICEAC50pct72hr</uiname>
    <valid_range>0.0</valid_range>
    <valid_range>10.0</valid_range>
    <fillValue>-999999.0</fillValue>
    <n3D>1</n3D>
    <levelsDesc>SFC</levelsDesc>
    <levels>
      <level>SFC</level>
    </levels>
  </gridParameterInfo>
  <gridParameterInfo xsi:type="parameterInfo" xmlns:xsi="http://www.w3.org/2001/XMLSchema-instance">
    <short_name>ficeac75pct72hr</short_name>
    <long_name>75th percentile Flat Ice Accumulation 72 hour</long_name>
    <units>m</units>
    <udunits>meter</udunits>
    <uiname>FICEAC75pct72hr</uiname>
    <valid_range>0.0</valid_range>
    <valid_range>10.0</valid_range>
    <fillValue>-999999.0</fillValue>
    <n3D>1</n3D>
    <levelsDesc>SFC</levelsDesc>
    <levels>
      <level>SFC</level>
    </levels>
  </gridParameterInfo>
  <gridParameterInfo xsi:type="parameterInfo" xmlns:xsi="http://www.w3.org/2001/XMLSchema-instance">
    <short_name>ficeac90pct72hr</short_name>
    <long_name>90th percentile Flat Ice Accumulation 72 hour</long_name>
    <units>m</units>
    <udunits>meter</udunits>
    <uiname>FICEAC90pct72hr</uiname>
    <valid_range>0.0</valid_range>
    <valid_range>10.0</valid_range>
    <fillValue>-999999.0</fillValue>
    <n3D>1</n3D>
    <levelsDesc>SFC</levelsDesc>
    <levels>
      <level>SFC</level>
    </levels>
  </gridParameterInfo>
  <gridParameterInfo xsi:type="parameterInfo" xmlns:xsi="http://www.w3.org/2001/XMLSchema-instance">
    <short_name>ficeac95pct72hr</short_name>
    <long_name>95th percentile Flat Ice Accumulation 72 hour</long_name>
    <units>m</units>
    <udunits>meter</udunits>
    <uiname>FICEAC95pct72hr</uiname>
    <valid_range>0.0</valid_range>
    <valid_range>10.0</valid_range>
    <fillValue>-999999.0</fillValue>
    <n3D>1</n3D>
    <levelsDesc>SFC</levelsDesc>
    <levels>
      <level>SFC</level>
    </levels>
  </gridParameterInfo>
  <gridParameterInfo xsi:type="parameterInfo" xmlns:xsi="http://www.w3.org/2001/XMLSchema-instance">
    <short_name>pcpdur12hr</short_name>
    <long_name>Precipitation Duration 12 hr</long_name>
    <units>inch</units>
    <udunits>inch</udunits>
    <uiname>PCPDUR12hr</uiname>
    <valid_range>0.0</valid_range>
    <valid_range>12.0</valid_range>
    <fillValue>-999999.0</fillValue>
    <n3D>1</n3D>
    <levelsDesc>SFC</levelsDesc>
    <levels>
      <level>SFC</level>
    </levels>
  </gridParameterInfo>
  <gridParameterInfo xsi:type="parameterInfo" xmlns:xsi="http://www.w3.org/2001/XMLSchema-instance">
    <short_name>totsn5pct24hr</short_name>
    <long_name>5th percentile Total snowfall</long_name>
    <units>m</units>
    <udunits>meter</udunits>
    <uiname>Totsn5pct24hr</uiname>
    <valid_range>0.0</valid_range>
    <valid_range>100.0</valid_range>
    <fillValue>-999999.0</fillValue>
    <n3D>1</n3D>
    <levelsDesc>SFC</levelsDesc>
    <levels>
      <level>SFC</level>
    </levels>
  </gridParameterInfo>
  <gridParameterInfo xsi:type="parameterInfo" xmlns:xsi="http://www.w3.org/2001/XMLSchema-instance">
    <short_name>totsn10pct24hr</short_name>
    <long_name>10th percentile Total snowfall</long_name>
    <units>m</units>
    <udunits>meter</udunits>
    <uiname>Totsn10pct24hr</uiname>
    <valid_range>0.0</valid_range>
    <valid_range>100.0</valid_range>
    <fillValue>-999999.0</fillValue>
    <n3D>1</n3D>
    <levelsDesc>SFC</levelsDesc>
    <levels>
      <level>SFC</level>
    </levels>
  </gridParameterInfo>
  <gridParameterInfo xsi:type="parameterInfo" xmlns:xsi="http://www.w3.org/2001/XMLSchema-instance">
    <short_name>totsn25pct24hr</short_name>
    <long_name>25th percentile Total snowfall</long_name>
    <units>m</units>
    <udunits>meter</udunits>
    <uiname>Totsn25pct24hr</uiname>
    <valid_range>0.0</valid_range>
    <valid_range>100.0</valid_range>
    <fillValue>-999999.0</fillValue>
    <n3D>1</n3D>
    <levelsDesc>SFC</levelsDesc>
    <levels>
      <level>SFC</level>
    </levels>
  </gridParameterInfo>
  <gridParameterInfo xsi:type="parameterInfo" xmlns:xsi="http://www.w3.org/2001/XMLSchema-instance">
    <short_name>totsn50pct24hr</short_name>
    <long_name>50th percentile Total snowfall</long_name>
    <units>m</units>
    <udunits>meter</udunits>
    <uiname>Totsn50pct24hr</uiname>
    <valid_range>0.0</valid_range>
    <valid_range>100.0</valid_range>
    <fillValue>-999999.0</fillValue>
    <n3D>1</n3D>
    <levelsDesc>SFC</levelsDesc>
    <levels>
      <level>SFC</level>
    </levels>
  </gridParameterInfo>
  <gridParameterInfo xsi:type="parameterInfo" xmlns:xsi="http://www.w3.org/2001/XMLSchema-instance">
    <short_name>totsn75pct24hr</short_name>
    <long_name>75th percentile Total snowfall</long_name>
    <units>m</units>
    <udunits>meter</udunits>
    <uiname>Totsn75pct24hr</uiname>
    <valid_range>0.0</valid_range>
    <valid_range>100.0</valid_range>
    <fillValue>-999999.0</fillValue>
    <n3D>1</n3D>
    <levelsDesc>SFC</levelsDesc>
    <levels>
      <level>SFC</level>
    </levels>
  </gridParameterInfo>
  <gridParameterInfo xsi:type="parameterInfo" xmlns:xsi="http://www.w3.org/2001/XMLSchema-instance">
    <short_name>totsn90pct24hr</short_name>
    <long_name>90th percentile Total snowfall</long_name>
    <units>m</units>
    <udunits>meter</udunits>
    <uiname>Totsn90pct24hr</uiname>
    <valid_range>0.0</valid_range>
    <valid_range>100.0</valid_range>
    <fillValue>-999999.0</fillValue>
    <n3D>1</n3D>
    <levelsDesc>SFC</levelsDesc>
    <levels>
      <level>SFC</level>
    </levels>
  </gridParameterInfo>
  <gridParameterInfo xsi:type="parameterInfo" xmlns:xsi="http://www.w3.org/2001/XMLSchema-instance">
    <short_name>totsn95pct24hr</short_name>
    <long_name>95th percentile Total snowfall</long_name>
    <units>m</units>
    <udunits>meter</udunits>
    <uiname>Totsn95pct24hr</uiname>
    <valid_range>0.0</valid_range>
    <valid_range>100.0</valid_range>
    <fillValue>-999999.0</fillValue>
    <n3D>1</n3D>
    <levelsDesc>SFC</levelsDesc>
    <levels>
      <level>SFC</level>
    </levels>
  </gridParameterInfo>
  <gridParameterInfo xsi:type="parameterInfo" xmlns:xsi="http://www.w3.org/2001/XMLSchema-instance">
    <short_name>totsn5pct48hr</short_name>
    <long_name>5th percentile Total snowfall</long_name>
    <units>m</units>
    <udunits>meter</udunits>
    <uiname>Totsn5pct48hr</uiname>
    <valid_range>0.0</valid_range>
    <valid_range>100.0</valid_range>
    <fillValue>-999999.0</fillValue>
    <n3D>1</n3D>
    <levelsDesc>SFC</levelsDesc>
    <levels>
      <level>SFC</level>
    </levels>
  </gridParameterInfo>
  <gridParameterInfo xsi:type="parameterInfo" xmlns:xsi="http://www.w3.org/2001/XMLSchema-instance">
    <short_name>totsn10pct48hr</short_name>
    <long_name>10th percentile Total snowfall</long_name>
    <units>m</units>
    <udunits>meter</udunits>
    <uiname>Totsn10pct48hr</uiname>
    <valid_range>0.0</valid_range>
    <valid_range>100.0</valid_range>
    <fillValue>-999999.0</fillValue>
    <n3D>1</n3D>
    <levelsDesc>SFC</levelsDesc>
    <levels>
      <level>SFC</level>
    </levels>
  </gridParameterInfo>
  <gridParameterInfo xsi:type="parameterInfo" xmlns:xsi="http://www.w3.org/2001/XMLSchema-instance">
    <short_name>totsn25pct48hr</short_name>
    <long_name>25th percentile Total snowfall</long_name>
    <units>m</units>
    <udunits>meter</udunits>
    <uiname>Totsn25pct48hr</uiname>
    <valid_range>0.0</valid_range>
    <valid_range>100.0</valid_range>
    <fillValue>-999999.0</fillValue>
    <n3D>1</n3D>
    <levelsDesc>SFC</levelsDesc>
    <levels>
      <level>SFC</level>
    </levels>
  </gridParameterInfo>
  <gridParameterInfo xsi:type="parameterInfo" xmlns:xsi="http://www.w3.org/2001/XMLSchema-instance">
    <short_name>totsn50pct48hr</short_name>
    <long_name>50th percentile Total snowfall</long_name>
    <units>m</units>
    <udunits>meter</udunits>
    <uiname>Totsn50pct48hr</uiname>
    <valid_range>0.0</valid_range>
    <valid_range>100.0</valid_range>
    <fillValue>-999999.0</fillValue>
    <n3D>1</n3D>
    <levelsDesc>SFC</levelsDesc>
    <levels>
      <level>SFC</level>
    </levels>
  </gridParameterInfo>
  <gridParameterInfo xsi:type="parameterInfo" xmlns:xsi="http://www.w3.org/2001/XMLSchema-instance">
    <short_name>totsn75pct48hr</short_name>
    <long_name>75th percentile Total snowfall</long_name>
    <units>m</units>
    <udunits>meter</udunits>
    <uiname>Totsn75pct48hr</uiname>
    <valid_range>0.0</valid_range>
    <valid_range>100.0</valid_range>
    <fillValue>-999999.0</fillValue>
    <n3D>1</n3D>
    <levelsDesc>SFC</levelsDesc>
    <levels>
      <level>SFC</level>
    </levels>
  </gridParameterInfo>
  <gridParameterInfo xsi:type="parameterInfo" xmlns:xsi="http://www.w3.org/2001/XMLSchema-instance">
    <short_name>totsn90pct48hr</short_name>
    <long_name>90th percentile Total snowfall</long_name>
    <units>m</units>
    <udunits>meter</udunits>
    <uiname>Totsn90pct48hr</uiname>
    <valid_range>0.0</valid_range>
    <valid_range>100.0</valid_range>
    <fillValue>-999999.0</fillValue>
    <n3D>1</n3D>
    <levelsDesc>SFC</levelsDesc>
    <levels>
      <level>SFC</level>
    </levels>
  </gridParameterInfo>
  <gridParameterInfo xsi:type="parameterInfo" xmlns:xsi="http://www.w3.org/2001/XMLSchema-instance">
    <short_name>totsn95pct48hr</short_name>
    <long_name>95th percentile Total snowfall</long_name>
    <units>m</units>
    <udunits>meter</udunits>
    <uiname>Totsn95pct48hr</uiname>
    <valid_range>0.0</valid_range>
    <valid_range>100.0</valid_range>
    <fillValue>-999999.0</fillValue>
    <n3D>1</n3D>
    <levelsDesc>SFC</levelsDesc>
    <levels>
      <level>SFC</level>
    </levels>
  </gridParameterInfo>

  <gridParameterInfo xsi:type="parameterInfo" xmlns:xsi="http://www.w3.org/2001/XMLSchema-instance">
    <short_name>totsn5pct72hr</short_name>
    <long_name>5th percentile Total snowfall</long_name>
    <units>m</units>
    <udunits>meter</udunits>
    <uiname>Totsn5pct72hr</uiname>
    <valid_range>0.0</valid_range>
    <valid_range>100.0</valid_range>
    <fillValue>-999999.0</fillValue>
    <n3D>1</n3D>
    <levelsDesc>SFC</levelsDesc>
    <levels>
      <level>SFC</level>
    </levels>
  </gridParameterInfo>
  <gridParameterInfo xsi:type="parameterInfo" xmlns:xsi="http://www.w3.org/2001/XMLSchema-instance">
    <short_name>totsn10pct72hr</short_name>
    <long_name>10th percentile Total snowfall</long_name>
    <units>m</units>
    <udunits>meter</udunits>
    <uiname>Totsn10pct72hr</uiname>
    <valid_range>0.0</valid_range>
    <valid_range>100.0</valid_range>
    <fillValue>-999999.0</fillValue>
    <n3D>1</n3D>
    <levelsDesc>SFC</levelsDesc>
    <levels>
      <level>SFC</level>
    </levels>
  </gridParameterInfo>
  <gridParameterInfo xsi:type="parameterInfo" xmlns:xsi="http://www.w3.org/2001/XMLSchema-instance">
    <short_name>totsn25pct72hr</short_name>
    <long_name>25th percentile Total snowfall</long_name>
    <units>m</units>
    <udunits>meter</udunits>
    <uiname>Totsn25pct72hr</uiname>
    <valid_range>0.0</valid_range>
    <valid_range>100.0</valid_range>
    <fillValue>-999999.0</fillValue>
    <n3D>1</n3D>
    <levelsDesc>SFC</levelsDesc>
    <levels>
      <level>SFC</level>
    </levels>
  </gridParameterInfo>
  <gridParameterInfo xsi:type="parameterInfo" xmlns:xsi="http://www.w3.org/2001/XMLSchema-instance">
    <short_name>totsn50pct72hr</short_name>
    <long_name>50th percentile Total snowfall</long_name>
    <units>m</units>
    <udunits>meter</udunits>
    <uiname>Totsn50pct72hr</uiname>
    <valid_range>0.0</valid_range>
    <valid_range>100.0</valid_range>
    <fillValue>-999999.0</fillValue>
    <n3D>1</n3D>
    <levelsDesc>SFC</levelsDesc>
    <levels>
      <level>SFC</level>
    </levels>
  </gridParameterInfo>
  <gridParameterInfo xsi:type="parameterInfo" xmlns:xsi="http://www.w3.org/2001/XMLSchema-instance">
    <short_name>totsn75pct72hr</short_name>
    <long_name>75th percentile Total snowfall</long_name>
    <units>m</units>
    <udunits>meter</udunits>
    <uiname>Totsn75pct72hr</uiname>
    <valid_range>0.0</valid_range>
    <valid_range>100.0</valid_range>
    <fillValue>-999999.0</fillValue>
    <n3D>1</n3D>
    <levelsDesc>SFC</levelsDesc>
    <levels>
      <level>SFC</level>
    </levels>
  </gridParameterInfo>
  <gridParameterInfo xsi:type="parameterInfo" xmlns:xsi="http://www.w3.org/2001/XMLSchema-instance">
    <short_name>totsn90pct72hr</short_name>
    <long_name>90th percentile Total snowfall</long_name>
    <units>m</units>
    <udunits>meter</udunits>
    <uiname>Totsn90pct72hr</uiname>
    <valid_range>0.0</valid_range>
    <valid_range>100.0</valid_range>
    <fillValue>-999999.0</fillValue>
    <n3D>1</n3D>
    <levelsDesc>SFC</levelsDesc>
    <levels>
      <level>SFC</level>
    </levels>
  </gridParameterInfo>
  <gridParameterInfo xsi:type="parameterInfo" xmlns:xsi="http://www.w3.org/2001/XMLSchema-instance">
    <short_name>totsn95pct72hr</short_name>
    <long_name>95th percentile Total snowfall</long_name>
    <units>m</units>
    <udunits>meter</udunits>
    <uiname>Totsn95pct72hr</uiname>
    <valid_range>0.0</valid_range>
    <valid_range>100.0</valid_range>
    <fillValue>-999999.0</fillValue>
    <n3D>1</n3D>
    <levelsDesc>SFC</levelsDesc>
    <levels>
      <level>SFC</level>
    </levels>
  </gridParameterInfo>

  <gridParameterInfo xsi:type="parameterInfo" xmlns:xsi="http://www.w3.org/2001/XMLSchema-instance">
    <short_name>dswrf</short_name>
    <long_name>Downward short-wave radiation flux</long_name>
    <units>m</units>
    <udunits>meter</udunits>
    <uiname>Dswrf</uiname>
    <valid_range>0.0</valid_range>
    <valid_range>600.0</valid_range>
    <fillValue>-999999.0</fillValue>
    <n3D>1</n3D>
    <levelsDesc>SFC</levelsDesc>
    <levels>
      <level>SFC</level>
    </levels>
  </gridParameterInfo>
  <gridParameterInfo xsi:type="parameterInfo" xmlns:xsi="http://www.w3.org/2001/XMLSchema-instance">
    <short_name>frzspr</short_name>
    <long_name>Freezing Spray</long_name>
    <units>1</units>
    <udunits>one</udunits>
    <uiname>FrzSpr</uiname>
    <valid_range>0</valid_range>
    <valid_range>3</valid_range>
    <fillValue>-999999.0</fillValue>
    <n3D>1</n3D>
    <levelsDesc>SFC</levelsDesc>
    <levels>
      <level>SFC</level>
    </levels>
  </gridParameterInfo>
  <gridParameterInfo xsi:type="parameterInfo" xmlns:xsi="http://www.w3.org/2001/XMLSchema-instance">
    <short_name>ws90pct</short_name>
    <long_name>90th percentile Wind speed</long_name>
    <units>m/s</units>
    <udunits>meter per second</udunits>
    <uiname>Ws90pct</uiname>
    <valid_range>0.0</valid_range>
    <valid_range>42.181</valid_range>
    <fillValue>-999999.0</fillValue>
    <n3D>1</n3D>
    <levelsDesc>FHAG 10</levelsDesc>
    <levels>
      <level>FHAG10</level>
    </levels>
  </gridParameterInfo>
</gridParamInfo>
